Workbook

Sheet COURS
A1: COURS DU MARCHÉ — BIJOU-R
A2: ⚠ Mettez à jour ces cellules jaunes pour recalculer tous les prix du catalogue
A3: OR
A4: Paramètre | B4: Valeur | C4: Unité | D4: Note
A5: Cours de l'or (à mettre à jour) | B5: 85 | C5: € / gramme | D5: Prix spot international converti en €/g
A7: DIAMANTS NATURELS
A8: Paramètre | B8: Valeur | C8: Unité | D8: Note
A9: Naturel — N1 Essentiel | B9: 1800 | C9: € / carat | D9: H-I / SI1-SI2 — entrée de gamme
A10: Naturel — N2 Sélection | B10: 3500 | C10: € / carat | D10: G-H / VS2 — bon rapport qualité/prix
A11: Naturel — N3 Prestige | B11: 6200 | C11: € / carat | D11: F-G / VS1 — haute joaillerie
A12: Naturel — N4 Excellence | B12: 10500 | C12: € / carat | D12: E-F / VVS1-VVS2 — très haute joaillerie
A13: Naturel — N5 Exception | B13: 18000 | C13: € / carat | D13: D / IF — collector
A15: DIAMANTS DE LABORATOIRE
A16: Paramètre | B16: Valeur | C16: Unité | D16: Note
A17: Labo — L1 Essentiel | B17: 420 | C17: € / carat | D17: H-I / SI1-SI2 — même qualité visuelle
A18: Labo — L2 Sélection | B18: 780 | C18: € / carat | D18: G-H / VS2
A19: Labo — L3 Prestige | B19: 1300 | C19: € / carat | D19: F-G / VS1
A20: Labo — L4 Excellence | B20: 2100 | C20: € / carat | D20: E-F / VVS1-VVS2
A21: Labo — L5 Exception | B21: 3500 | C21: € / carat | D21: D / IF

Sheet CONFIG
A1: CONFIGURATION — PARAMÈTRES FIXES
A2: OR & MÉTAUX
A3: Paramètre | B3: Valeur | C3: Unité | D3: Note
A4: Pureté or 18k | B4: 0.75 | C4: facteur | D4: 75% d'or pur dans l'alliage 18k
A5: Supplément or blanc (rhodium) | B5: 0.08 | C5: facteur +% | D5: Coût du plaquage rhodium
A6: Supplément or rose | B6: 0.02 | C6: facteur +% | D6: Alliage cuivre légèrement plus coûteux
A7: FABRICATION
A8: Paramètre | B8: Valeur | C8: Unité | D8: Note
A9: Main d'œuvre par défaut | B9: 180 | C9: € | D9: Modifiable ligne par ligne dans le catalogue
A10: Frais généraux fixes | B10: 25 | C10: € | D10: Emballage, écrin, certificat
A11: TARIFICATION
A12: Paramètre | B12: Valeur | C12: Unité | D12: Note
A13: Coefficient de marge | B13: 2.8 | C13: × | D13: Prix vente HT = prix revient × coefficient
A14: TVA | B14: 0.2 | C14: % | D14: 20% — France

Sheet CATALOGUE
A1: CATALOGUE PRODUITS — BIJOU-R
A2: IDENTITÉ PRODUIT | D2: MATIÈRES | G2: POIDS & FABRICATION | J2: COÛTS MATIÈRES | L2: PRIX CALCULÉS ✦ ne pas modifier
A3: Référence | B3: Nom du modèle | C3: Collection | D3: Métal | E3: Type diamant | F3: Niveau diamant | G3: Poids or (g) | H3: Carats | I3: Main d'œuvre (€) | J3: Coût or (€) | K3: Coût diamant (€) | L3: Prix de revient (€) | M3: Prix HT (€) | N3: Prix TTC (€)
A4: SOL-001-OB-N | B4: Solitaire Éclat | C4: Solitaires | D4: Or blanc | E4: Naturel | F4: N3 Prestige | G4: 3.2 | H4: 1 | I4: =CONFIG!$B$8 | J4: =ROUND(G4*COURS!$B$5*CONFIG!$B$5*IF(D4="Or blanc",1+CONFIG!B6,IF(D4="Or rose",1+CONFIG!B7,1)),2) | K4: =ROUND(H4*IF(E4="Naturel",IF(F4="N1 Essentiel",COURS!B9,IF(F4="N2 Sélection",COURS!B10,IF(F4="N3 Prestige",COURS!B11,IF(F4="N4 Excellence",COURS!B12,IF(F4="N5 Exception",COURS!B13,0))))),IF(F4="L1 Essentiel",COURS!B17,IF(F4="L2 Sélection",COURS!B18,IF(F4="L3 Prestige",COURS!B19,IF(F4="L4 Excellence",COURS!B20,IF(F4="L5 Exception",COURS!B21,0)))))),2) | L4: =ROUND(J4+K4+I4+CONFIG!$B$9,2) | M4: =ROUND(L4*CONFIG!$B$11,2) | N4: =ROUND(M4*(1+CONFIG!$B$12),2)
A5: SOL-001-OB-L | B5: Solitaire Éclat | C5: Solitaires | D5: Or blanc | E5: Labo | F5: L3 Prestige | G5: 3.2 | H5: 1 | I5: =CONFIG!$B$8 | J5: =ROUND(G5*COURS!$B$5*CONFIG!$B$5*IF(D5="Or blanc",1+CONFIG!B6,IF(D5="Or rose",1+CONFIG!B7,1)),2) | K5: =ROUND(H5*IF(E5="Naturel",IF(F5="N1 Essentiel",COURS!B9,IF(F5="N2 Sélection",COURS!B10,IF(F5="N3 Prestige",COURS!B11,IF(F5="N4 Excellence",COURS!B12,IF(F5="N5 Exception",COURS!B13,0))))),IF(F5="L1 Essentiel",COURS!B17,IF(F5="L2 Sélection",COURS!B18,IF(F5="L3 Prestige",COURS!B19,IF(F5="L4 Excellence",COURS!B20,IF(F5="L5 Exception",COURS!B21,0)))))),2) | L5: =ROUND(J5+K5+I5+CONFIG!$B$9,2) | M5: =ROUND(L5*CONFIG!$B$11,2) | N5: =ROUND(M5*(1+CONFIG!$B$12),2)
A6: SOL-001-OJ-N | B6: Solitaire Éclat | C6: Solitaires | D6: Or jaune | E6: Naturel | F6: N3 Prestige | G6: 3.2 | H6: 1 | I6: =CONFIG!$B$8 | J6: =ROUND(G6*COURS!$B$5*CONFIG!$B$5*IF(D6="Or blanc",1+CONFIG!B6,IF(D6="Or rose",1+CONFIG!B7,1)),2) | K6: =ROUND(H6*IF(E6="Naturel",IF(F6="N1 Essentiel",COURS!B9,IF(F6="N2 Sélection",COURS!B10,IF(F6="N3 Prestige",COURS!B11,IF(F6="N4 Excellence",COURS!B12,IF(F6="N5 Exception",COURS!B13,0))))),IF(F6="L1 Essentiel",COURS!B17,IF(F6="L2 Sélection",COURS!B18,IF(F6="L3 Prestige",COURS!B19,IF(F6="L4 Excellence",COURS!B20,IF(F6="L5 Exception",COURS!B21,0)))))),2) | L6: =ROUND(J6+K6+I6+CONFIG!$B$9,2) | M6: =ROUND(L6*CONFIG!$B$11,2) | N6: =ROUND(M6*(1+CONFIG!$B$12),2)
A7: SOL-001-OR-N | B7: Solitaire Éclat | C7: Solitaires | D7: Or rose | E7: Naturel | F7: N3 Prestige | G7: 3.2 | H7: 1 | I7: =CONFIG!$B$8 | J7: =ROUND(G7*COURS!$B$5*CONFIG!$B$5*IF(D7="Or blanc",1+CONFIG!B6,IF(D7="Or rose",1+CONFIG!B7,1)),2) | K7: =ROUND(H7*IF(E7="Naturel",IF(F7="N1 Essentiel",COURS!B9,IF(F7="N2 Sélection",COURS!B10,IF(F7="N3 Prestige",COURS!B11,IF(F7="N4 Excellence",COURS!B12,IF(F7="N5 Exception",COURS!B13,0))))),IF(F7="L1 Essentiel",COURS!B17,IF(F7="L2 Sélection",COURS!B18,IF(F7="L3 Prestige",COURS!B19,IF(F7="L4 Excellence",COURS!B20,IF(F7="L5 Exception",COURS!B21,0)))))),2) | L7: =ROUND(J7+K7+I7+CONFIG!$B$9,2) | M7: =ROUND(L7*CONFIG!$B$11,2) | N7: =ROUND(M7*(1+CONFIG!$B$12),2)
A8: PAV-001-OB-N | B8: Pavé Lumière | C8: Pavé | D8: Or blanc | E8: Naturel | F8: N2 Sélection | G8: 4.1 | H8: 0.48 | I8: =CONFIG!$B$8 | J8: =ROUND(G8*COURS!$B$5*CONFIG!$B$5*IF(D8="Or blanc",1+CONFIG!B6,IF(D8="Or rose",1+CONFIG!B7,1)),2) | K8: =ROUND(H8*IF(E8="Naturel",IF(F8="N1 Essentiel",COURS!B9,IF(F8="N2 Sélection",COURS!B10,IF(F8="N3 Prestige",COURS!B11,IF(F8="N4 Excellence",COURS!B12,IF(F8="N5 Exception",COURS!B13,0))))),IF(F8="L1 Essentiel",COURS!B17,IF(F8="L2 Sélection",COURS!B18,IF(F8="L3 Prestige",COURS!B19,IF(F8="L4 Excellence",COURS!B20,IF(F8="L5 Exception",COURS!B21,0)))))),2) | L8: =ROUND(J8+K8+I8+CONFIG!$B$9,2) | M8: =ROUND(L8*CONFIG!$B$11,2) | N8: =ROUND(M8*(1+CONFIG!$B$12),2)
A9: PAV-001-OB-L | B9: Pavé Lumière | C9: Pavé | D9: Or blanc | E9: Labo | F9: L2 Sélection | G9: 4.1 | H9: 0.48 | I9: =CONFIG!$B$8 | J9: =ROUND(G9*COURS!$B$5*CONFIG!$B$5*IF(D9="Or blanc",1+CONFIG!B6,IF(D9="Or rose",1+CONFIG!B7,1)),2) | K9: =ROUND(H9*IF(E9="Naturel",IF(F9="N1 Essentiel",COURS!B9,IF(F9="N2 Sélection",COURS!B10,IF(F9="N3 Prestige",COURS!B11,IF(F9="N4 Excellence",COURS!B12,IF(F9="N5 Exception",COURS!B13,0))))),IF(F9="L1 Essentiel",COURS!B17,IF(F9="L2 Sélection",COURS!B18,IF(F9="L3 Prestige",COURS!B19,IF(F9="L4 Excellence",COURS!B20,IF(F9="L5 Exception",COURS!B21,0)))))),2) | L9: =ROUND(J9+K9+I9+CONFIG!$B$9,2) | M9: =ROUND(L9*CONFIG!$B$11,2) | N9: =ROUND(M9*(1+CONFIG!$B$12),2)
A10: ALI-001-OB-N | B10: Alliance Éternité | C10: Alliances | D10: Or blanc | E10: Naturel | F10: N1 Essentiel | G10: 2.8 | H10: 0.3 | I10: =CONFIG!$B$8 | J10: =ROUND(G10*COURS!$B$5*CONFIG!$B$5*IF(D10="Or blanc",1+CONFIG!B6,IF(D10="Or rose",1+CONFIG!B7,1)),2) | K10: =ROUND(H10*IF(E10="Naturel",IF(F10="N1 Essentiel",COURS!B9,IF(F10="N2 Sélection",COURS!B10,IF(F10="N3 Prestige",COURS!B11,IF(F10="N4 Excellence",COURS!B12,IF(F10="N5 Exception",COURS!B13,0))))),IF(F10="L1 Essentiel",COURS!B17,IF(F10="L2 Sélection",COURS!B18,IF(F10="L3 Prestige",COURS!B19,IF(F10="L4 Excellence",COURS!B20,IF(F10="L5 Exception",COURS!B21,0)))))),2) | L10: =ROUND(J10+K10+I10+CONFIG!$B$9,2) | M10: =ROUND(L10*CONFIG!$B$11,2) | N10: =ROUND(M10*(1+CONFIG!$B$12),2)
A11: ALI-001-OJ-N | B11: Alliance Éternité | C11: Alliances | D11: Or jaune | E11: Naturel | F11: N1 Essentiel | G11: 2.8 | H11: 0.3 | I11: =CONFIG!$B$8 | J11: =ROUND(G11*COURS!$B$5*CONFIG!$B$5*IF(D11="Or blanc",1+CONFIG!B6,IF(D11="Or rose",1+CONFIG!B7,1)),2) | K11: =ROUND(H11*IF(E11="Naturel",IF(F11="N1 Essentiel",COURS!B9,IF(F11="N2 Sélection",COURS!B10,IF(F11="N3 Prestige",COURS!B11,IF(F11="N4 Excellence",COURS!B12,IF(F11="N5 Exception",COURS!B13,0))))),IF(F11="L1 Essentiel",COURS!B17,IF(F11="L2 Sélection",COURS!B18,IF(F11="L3 Prestige",COURS!B19,IF(F11="L4 Excellence",COURS!B20,IF(F11="L5 Exception",COURS!B21,0)))))),2) | L11: =ROUND(J11+K11+I11+CONFIG!$B$9,2) | M11: =ROUND(L11*CONFIG!$B$11,2) | N11: =ROUND(M11*(1+CONFIG!$B$12),2)
A12: ⟶ Ajouter vos produits à partir de cette ligne en copiant une ligne existante

Sheet EXPORT SHOPIFY
A1: EXPORT SHOPIFY — Format prêt pour import Matrixify
A2: Handle | B2: Title | C2: Body (HTML) | D2: Vendor | E2: Type | F2: Tags | G2: Published | H2: Option1 Name | I2: Option1 Value | J2: Option2 Name | K2: Option2 Value | L2: Option3 Name | M2: Option3 Value | N2: Variant SKU | O2: Variant Price | P2: Variant Compare At Price | Q2: Variant Inventory Qty | R2: Image Src | S2: Image Alt Text | T2: SEO Title | U2: SEO Description
A3: ℹ Remplissez cet onglet depuis le CATALOGUE en copiant Référence → Handle, Nom → Title, Prix TTC → Variant Price. Ajoutez les variantes de taille (une ligne par taille, même Handle). Exportez en .CSV pour Matrixify.
A4: solitaire-eclat-ob-n | B4: Solitaire Éclat — Or Blanc — Diamant Naturel | C4: <p>Description SEO à remplir</p> | D4: Bijou-R | E4: Bague Solitaire | F4: solitaire, diamant naturel, or blanc, fiançailles | G4: TRUE | H4: Taille | I4: 52 | J4: Métal | K4: Or blanc | L4: Diamant | M4: N3 Prestige | N4: SOL-001-OB-N-52 | O4: =CATALOGUE!N4 | Q4: 3 | R4: https://url-image.com/bague.jpg | S4: Solitaire Éclat diamant naturel 1ct or blanc | T4: Bague Solitaire Diamant 1ct Or Blanc — Bijou-R | U4: Découvrez notre solitaire Éclat, diamant naturel 1 carat F/VS1 serti en or blanc 18k.
